{
    "k": "Finite Field of size 37",
    "k_minimal_polynomial": "x + 36",
    "p": "37",
    "l": "5",
    "j1": "2",
    "j2": "3",
    "multiplicity": "2",
    "domain_curve": "Elliptic Curve defined by y^2 = x^3 + 33*x + 27 over Finite Field of size 37",
    "p_rank": "1",
    "fiber_polynomial": "31*t^2 + 18*t + 22",
    "splitting_field": "Finite Field of size 37",
    "splitting_field_minimal_polynomial": "x + 36",
    "isogeny_data": {
        "23": {
            "model": [
                "23",
                "14"
            ],
            "codomain_curve": "Elliptic Curve defined by y^2 = x^3 + 23*x + 14 over Finite Field of size 37",
            "abscissa": "25",
            "kernel_polynomial": "x^2 + 6*x + 35"
        },
        "17": {
            "model": [
                "19",
                "31"
            ],
            "codomain_curve": "Elliptic Curve defined by y^2 = x^3 + 19*x + 31 over Finite Field of size 37",
            "abscissa": "32",
            "kernel_polynomial": "x^2 + 21*x + 29"
        }
    }
}